<?xml version="1.0" encoding="ISO-8859-1"?>
	<!DOCTYPE NIR SYSTEM 'nircompleto.dtd'>
	<NIR tipo="originale" xmlns="http://www.normeinrete.it/nir/2.2/" xmlns:dsp="http://www.normeinrete.it/nir/disposizioni/2.2/" xmlns:h="http://www.w3.org/HTML/1998/html4" xmlns:xlink="http://www.w3.org/1999/xlink">
		<LeggeRegionale>
			<meta>
				<descrittori>
					<pubblicazione norm="19951216" num="25" tipo="BURM" />
					<entratainvigore norm="19951231" />
					<redazione id="red1" nome="" norm="" />
					<urn valore="urn:nir:regione.molise:legge:1995-12-15;30" />
					<materie vocabolario="Regione Molise">
						<materia valore="07.contabilità e contratti, bilanci, manovre finanziarie, armonizzazione dei bilanci pubblici e coordinamento della finanza pubblica" />
					</materie>
				</descrittori>
				<ciclodivita>
					<eventi>
						<evento data="20100530" fonte="rp1" id="t1" tipo="modifica" />
					</eventi>
					<relazioni>
						<passiva id="rp1" xlink:href="urn:nir:regione.molise:legge:2010;13" xlink:type="simple" />
					</relazioni>
				</ciclodivita>
			</meta>
			<?error 07.Contabilità e contratti, bilanci, manovre finanziarie, armonizzazione dei bilanci pubblici e coordinamento della finanza pubblica 
 
Bollettino 
Bollettino Ufficiale n. 25 del 16/12/95 
 
Oggetto 
Assestamento del bilancio 1995 
 
Abrogazioni 
Abrogata intera legge dalla legge n. 13/2010 art. allegato 1 
 
Modifiche 
 
 
?>
			<intestazione>
				<emanante>Regione Molise</emanante>
				<tipoDoc>Legge Regionale</tipoDoc>
				<dataDoc norm="19951215">15 Dicembre 1995</dataDoc>
				, n.
				<numDoc>30</numDoc>
				<titoloDoc>
					<rif xlink:href="urn:nir:regione.molise:legge:1977-12-03;44#art36" xlink:type="simple">Articolo 36 della legge regionale 3 dicembre 1977, n. 44</rif>
					- Assestamento del bilancio di competenza e di cassa 1995.
				</titoloDoc>
			</intestazione>
			<formulainiziale />
			<articolato>
				<articolo id="art1">
					<num />
					<comma id="art1-com1">
						<num />
						<corpo>abrogata intera legge dalla legge n. 13/2010 art. allegato 1</corpo>
					</comma>
				</articolo>
			</articolato>
			<formulafinale />
			<conclusione />
			<?error n. 281. 
 
   01501 - 211 - Quota variabile art. 9 anno 1994. Differenza attiva. 
 
   Delibera CIPE del 13 marzo 1995 - +518.545.000 - +518.545.000. 
 
   01796 - 212 - Assegnazione di fondi dello Stato ai sensi della 
 
   legge 201/91 e 752/1986. Assegnazione 1994 - +15.264.000.000 - 
 
   +15.264.000.000. 
 
   01803 - 212 - Assegnazioni fondi dello Stato per il programma 
 
   operativo relativo alla divulgazione agricola ed attività 
 
   connesse misura n. 4 reg. CEE n. 2052/88 - +1.896.115 - 
 
   +1.896.115. 
 
   01804 - 212 - Contributi CEE a seguito reg. 2052/88. 
 
   Ob. 1 mis. 6 agrivideotel 2. Programma 1992 - -1.896.115 - 
 
   -1.896.115. 
 
   02058 - 222 - Fondi CEE relativi al piano di sviluppo 
 
   regionale 1994 - 1999. Quadro comunitario di sostegno approvato 
 
   dalla commissione U.E. in data 5 luglio 1994. Regolamento CEE 
 
   n. 2081/93 del Consiglio del 20 luglio 1993. Nota del Ministro 
 
   del bilancio n. 5/0446 del 21 luglio 1994. Quota 1994-1995 
 
   38.538,543 x 2.000. Decisione CEE C. (94) 1835 del 29 luglio 
 
   1994, decisione CEE 20 dicembre 1994 C. (94) 3766. Fondi F.S.E. 
 
   e FERS - -147.331.700.000 - -147.331.700.000. 
 
   02059 - 222 - Fondi nazionali per il piano di sviluppo regionale 
 
   1994 - 1999. Regolamento CEE n. 2081/93. Quota 1994-1995 ECU 
 
   18.419 x 2.000. Decisione CEE C. (94) del 27 luglio 1994, 
 
   decisione 20 dicembre 1994 C. (94) n. 3766 - -62.701.900.000 - 
 
   -62.701.900.000. 
 
   02060 - 222 - Somme attribuite alla Regione per il finanziamento 
 
   dei programmi regionali di sviluppo. Art. 13 legge 64/86. Quota 
 
   1993-1994. Delibera CIPE 7 giugno 1993 - -7.012.000.000 - 
 
   +14.142.000.000 - +7.130.000.000. 
 
   02115 - 222 - Somme attribuite alla Regione dallo Stato per 
 
   il finanziamento dei sottoprogrammi PIM Molise. Anno 1991 - 
 
   +17.866.278.000 -. 
 
   02136 - 222 - Fondi CEE relativi al POP Molise 1994-1999. 
 
   Regolamento CEE n. 2052/88 modificato dal regolamento CEE 
 
   n. 2081/93. Decisione CEE n. C (94) 1835 del 29 luglio 1994 
 
   e n. C (94) 3766 del 20 dicembre 1994. Annualità 1994 e 1995. 
 
   Fondi F.E.R.S. - +45.076.000.000 - +45.076.000.000. 
 
   02137 - 222 - Fondi CEE relativi al POP Molise 1994-1999. 
 
   Regolamento CEE n. 2052/88 modificato dal regolamento CEE 
 
   n. 2081/93. Decisione CEE n. C (94) 1835 del 29 luglio 1994 
 
   e n. C (94) 3766 del 20 dicembre 1994. Annualità 1994 e 1995 
 
   fondi F.S.E. - +32.000.000.000 - +32.000.000.000. 
 
   02139 - 222 - Compartecipazione nazionale al POP Molise 
 
   1994-1999. Regolamento CEE n. 2052/88, modificato dal regolamento 
 
   n. 2081/93. Contributo nazionale e coofinanziamento sui 
 
   fondi F.E.S.R. Annualità 1994 e 1995 - +27.906.000.000 - 
 
   +27.906.000.000. 
 
   02140 - 222 - Compartecipazione nazionale al POP Molise 
 
   1994-1999. Regolamento CEE n. 2052/88, modificato dal regolamento 
 
   CEE n. 2081/93. Contributo nazionale e coofinanziamento 
 
   sui fondi F.S.E. Annualità 1994 e 1995 - +8.932.000.000 - 
 
   +8.932.000.000. 
 
   Categoria 3 
 
   Fondi derivati da altre assegnazioni dello Stato a scopi 
 
   particolari. 
 
   03017 - 231 - Assegnazioni di fondi dello Stato per 
 
   contributi in conto interessi per progetti e singole opere 
 
   per la realizzazione di strutture turistiche, ricettive e 
 
   tecnologiche ai sensi degli artt. 1 e 2 della legge 30 dicembre 
 
   1988, n. 556 - -196.000.000 - -196.000.000. 
 
   07001 - 232 - Assegnazione di fondi dello Stato ex art. 11 
 
   comma 4. Legge 10 aprile 1981, n.151 per investimenti nel 
 
   settore dei trasporti pubblici locali. Oneri 1995 - 
 
   -1.671.030.000. 
 
   07012 - 236 - Assegnazioni dello Stato di fondi, parte in conto 
 
   capitale. Quota anno 1995. Delibera CIPE del 13 marzo 1995 - 
 
   +3.010.000.000 - +3.010.000.000. 
 
   Categoria 2 
 
   Rendite patrimoniali e proventi del demanio. 
 
   08600 - 326 - Rendite dei beni del demanio e del patrimonio 
 
   regionale - +455.214.700 - +455.214.700. 
 
   Categoria 6 
 
   Recuperi e rimborsi. 
 
   10016 - 362 - Rimborso da privati ed Enti per somme assegnate 
 
   e non usufruite relative concessioni contributive regionali - 
 
   +847.500 - +847.500. 
 
   Categoria 7 
 
   Partite che si compensano nella spesa. 
 
   10050 - 372 - Rimborso da parte del Consiglio Regionale di 
 
   somme pignorate nell'anno 1994 sul tesoriere regionale per 
 
   conto di Zampino Lucio - +165.111.455 - +165.111.455. 
 
   10073 - 372 - Acquisizione di mezzi finanziari dalla FINMOLISE 
 
   per anticipazione agli Enti attuatori per gli interventi ai 
 
   sensi della legge 64/86. Delibera Giunta n. 4081/95 - 
 
   +50.000.000.000 - +50.000.000.000. 
 
   Categoria 2 
 
   Eredit&#x85;, donazioni ed altri trasferimenti di capitali non 
 
   dello Stato. 
 
   10716 - 422 - Trasferimenti di capitali dalla CEE per il piano 
 
   1994 comunitario di sostegno approvato con decisione n. C. (94) 
 
   1835. Fondo sociale europeo del (75%) obiettivo n. 1 - 
 
   -7.694.890.000 - -7.694.890.000. 
 
   10718 - 422 - Trasferimenti di capitali dalla CEE per il piano 
 
   1994 comunitario di sostegno approvato con decisione n. C (94) 
 
   1835. Fondo sociale europeo (75%). Obiettivo n. 3 - 
 
   +5.180.000.000 - +5.180.000.000. 
 
   10719 - 422 - Trasferimenti di capitali dalla CEE per il piano 
 
   1994 comunitario di sostegno approvato con decisione C.(94) 
 
   1835. Fondo sociale europeo (75%). Obiettivo n. 4 - 
 
   +2.514.890.000 - +2.514.890.000. 
 
   Categoria 3 
 
   Rimborso di crediti e di anticipazioni. 
 
   11265 - 436 - Recupero da parte dello Stato di fondi anticipati 
 
   dalla Regione nell'anno 1989 per il pagamento dei contributi 
 
   a favore delle Societ&#x85; Automobilistiche Regionali - 
 
   +5.216.401.000 - +5.216.401.000. 
 
   Categoria 2 
 
   Anticipazioni di cassa ed altre operazioni di credito a breve 
 
   termine. 
 
   11600 - 521 - Anticipazioni di cassa ed altre operazioni a breve 
 
   termine - +5.000.000.000 - +5.000.000.000. 
 
   Titolo VI 
 
   Entrate per partite di giro. 
 
   Categoria 1 
 
   Partite di giro. 
 
   12110 - 613 - Ritenute IRPEF su assegni, indennità e compensi - 
 
   +8.828.841 - +8.828.841. 
 
   12800 - 613 - Movimenti e giri contabili - +112.883.528 - 
 
   +112.883.528. 
 
   12906 - 613 - Prelevamenti di fondi disponibili sul conto corrente 
 
   acceso presso il tesoro dello Stato n. 22929/1018 &lt;&lt;Regione 
 
   Molise contributo sanitario&gt;&gt; - +48.635.000.000 - 
 
   +48.635.000.000. 
 
   Totale generale entrate: 
 
   +73.149.930.080 - +26.947.132.491 - +57.613.527.392. 
 
   Allegato &lt;&lt;B&gt;&gt; 
 
   ASSESTAMENTO DELLE USCITE 
 
   (Voci in ordine di riferimento: Classificazione - Capitolo - 
 
   Oggetto della previsione - Residui al 31 dicembre 1994 - 
 
   Previsioni: Competenza - Cassa). 
 
   Sezione 1 
 
   Servizi istituzionali  ed amministrativi centrale 
 
   Rubrica 1 
 
   Servizi istituzionali. 
 
   Settore 1 
 
   Consiglio Regionale. 
 
   11141101011011 - 00300 - Spese postali, telefoniche, di 
 
   cancelleria, di resocontazione, biblioteca e in genere di 
 
   economato, spese correnti per attrezzature ed arredamento, 
 
   spese per manutenzione ed acquisto automezzi, illuminazione, 
 
   riscaldamento, fitto e pulizia locali (legge 6 dicembre 1973, 
 
   n. 853 legge regionale 25 giugno 1976, n. 21, legge regionale 
 
   n. 13 del 12 aprile 1995). (Spesa obbligatoria). Legge 
 
   regionale n. 13 del 12 aprile 1995 - +300.000.000 - 
 
   +300.000.000. 
 
   11142101011011 - 00700 - Spese relative al fondo di 
 
   orevidenza dei consiglieri art. 2, 3 della legge regionale 
 
   n. 15/1995 - +2.500.000.000 - +2.500.000.000. 
 
   11130101011021 - 04305 - Oneri per la corresponsione 
 
   dell'indennità di anzianità al personale previsto dagli 
 
   artt. 3 e 5 della legge regionale 5 settembre 1984 n. 27 e 
 
   legge regionale 14 dicembre 1990 n. 31. Spesa obbligatoria. 
 
   (Oneri 1995 e pregressi) - +250.000.000 - +250.000.000. 
 
   11141101011021 - 04720 - Oneri per il servizio mensa per il 
 
   personale regionale. (art. 32 legge 29 aprile 1985 n. 13 legge 
 
   regionale 14 dicembre 1990 n. 31). Spesa obbligatoria - 
 
   -450.000.000 - -450.000.000. 
 
   11121101011021 - 04905 - Fondo per il miglioramento 
 
   dell'efficienza dei servizi (comprende straordinario, 
 
   produttività, reperibilità, turnazione e rischio). 
 
   (Legge regionale 14 dicembre 1990 n. 31). Spesa obbligatoria 
 
   - -209.000.000 - -209.000.000. 
 
   11141101011021 - 05820 - Spese per selezione, corsi e concorsi. 
 
   (Spesa obbligatoria). Legge regionale n. 10 del 30 giugno 1994 
 
   - -250.000.000 - -250.000.000. 
 
   11141101011021 - 05825 - Spese per l'attuazione del progetto 
 
   ouverture. Progetto di interscambio di esperienze fra le 
 
   autonomie locali. Finanziamento CEE - +59.019.840 - +59.019.840. 
 
                     &lt;&lt;&lt;&lt;&lt;&lt;segue&lt;&lt;&lt;&lt;&lt;&lt;&lt;&lt; 
 
          -- parte seconda  --- 
 
   Settore 2 
 
   Studi e ricerche (servizio gabinetto e affari generali della 
 
   Pres. Giun.). 
 
   11142101011022 - 06500 - Spese e contributi per convegni, 
 
   indagini conoscitive, studi, ricerche ed altre attività per 
 
   fini istituzionali (legge regionale 27 ottobre 1972 n. 18) 
 
   spesa obbligatoria - +26.000.000 - +26.000.000. 
 
   Settore 3 
 
   Spese di funzionamento (Servizio ragioneria generale). 
 
   11142101011023 - 06700 - Spese per liti, transazioni arbitraggi 
 
   di giudizio ed accessori spesa obbligatoria - +400.000.000 - 
 
   +400.000.000. 
 
   11142101011027 - 06785 - Oneri da sostenere per pignoramenti 
 
   eseguiti dal tribunale sul fondo di Tesoreria Credito Molisano 
 
   - +259.660.533 - +259.660.533. 
 
   11142101011023 - 06800 - Oneri per la promozione di iniziative 
 
   di pubblico interesse. Legge regionale n. 7 del 19 maggio 1987 
 
   - +100.000.000 - +100.000.000. 
 
   11141101011023 - 07200 - Spese per manutenzione, riparazioni 
 
   ed adattamento locali e relativi impianti di immobili 
 
   non di proprietà della Regione. (Spesa obbligatoria)- 
 
   +20.000.000 - +20.000.000. 
 
   11146101011023 - 07700 - Imposte e tasse erariali a carico 
 
   della Regione. (Spesa obbligatoria) - -90.000.000- -90.000.000. 
 
   11143101011023 - 07800 - Spese per l'acquisto e la manutenzione 
 
   di mobili, suppellettili etc. per gli uffici. (Spesa 
 
   obbligatoria)- +20.000.000 - +20.000.000. 
 
   11141101011023 - 07500 - Spese per impianti telefonici 
 
   (canoni, conversazioni interurbane, centralini ecc.). 
 
   (Spesa obbligatoria) - +115.000.000 - +115.000.000. 
 
   11141101011023 - 08150 - Spese per la vigilanza notturna 
 
   e diurna dei locali adibiti ad uffici e autorimesse regionali. 
 
   (Spesa obbligatoria). Oneri 95 e retro - +420.000.000 - 
 
   +420.000.000. 
 
   11141101011023 - 08200 - Spese postali e telegrafiche. 
 
   (Spesa obbligatoria) - +15.000.000 - +15.000.000. 
 
   11141101011023 - 08300 - Spese per l'acquisto di materiali 
 
   di cancelleria, per stampati, riproduzioni grafiche, per 
 
   rilegatura e per altre di ufficio compreso bollatura di 
 
   atti e carta bollata. (Spesa obbligatoria) - +10.000.000 - 
 
   +10.000.000. 
 
   11141101011023 - 08350 - Spese per l'acquisto, manutenzione e 
 
   funzionamento di apparecchiature meccanografiche. 
 
   (Spesa obbligatoria) - +10.000.000. - +10.000.000. 
 
   11143101011023 - 08400 - Spese per l'acquisto ed il noleggio 
 
   di automezzi, l'esercizio, manutenzione ed assicurazioni 
 
   R.C.A. (spesa obbligatoria) - -50.000.000 - -50.000.000. 
 
   11182101011023 - 08706 - Spese per caàpagne pubblicitarie 
 
   e di formazione delle proprie attivit&#x85; attraverso emittenti 
 
   televisive e radiofoniche locali. Legge 27 ottobre 1993 n. 422 - 
 
   -138.000.000 - -137.300.000. 
 
   Settore 4 
 
   Automazione e informatica (servizio organizzazione e 
 
   informatica). 
 
   11241101011024 - 09500 - Spese per la meccanizzazione dei 
 
   servizi amministrativi contabili o di gestione di bilancio. 
 
   (Spesa obbligatoria) - -100.000.000 - -100.000.000. 
 
   Settore 7 
 
   Acquisto costruzione riattamento ed ampliamento di edifici 
 
   Regionali. 
 
   11210301011027 - 11401 - Spese per la costruzione, il 
 
   riattamento di edifici regionali e manutenzione straordinaria. 
 
   (Spesa obbligatoria) - +141.065.906 - +141.065.906. 
 
   11210301011027 - 11408 - Spese relative all'accertamento e 
 
   opere di adeguamento degli edifici utilizzati 
 
   dall'amministrazione alle norme sulla prevenzione incendi - 
 
   +110.934.094 - +110.934.094. 
 
   Settore 8 
 
   Partecipazione a società finanziarie. 
 
   21251312321028 - 11535 - Compensi ed oneri alla FINMOLISE S.p.A. 
 
   a seguito di convenzioni per interventi speciali previsti 
 
   dall'articolo n. 5 legge regionale 24 marzo 1979, n. 11 - 
 
   +3.314.219.541 - +3.314.219.541. 
 
   Rubrica 3 
 
   Programmi Regionali di sviluppo. 
 
   Settore 1 
 
   Interv. plurisett. secondo piano annuale di attuazione 
 
   sub-azione 6.3. 
 
   21280206151031 - 11915 - Oneri per la realizzazione di opere 
 
   inerenti il II piano di attuazione e rientranti nei progetti 
 
   dell'attuazione organica n. 63. Legge 1 marzo 1986 n. 64. 
 
   Delibera CIPE 3 agosto 1988 - -1.269.049.250 - -1.269.049.250. 
 
   Settore 3 
 
   Programm. economica studi 2&#xF8; piano annuale di attuaz. e 
 
   azione org. 6.3. 
 
   21280206151033 - 11923 - Oneri per la realizzazione di studi 
 
   inerenti il secondo piano di attuazione e rientranti nei 
 
   progetti di importo inferiore o uguale a 200 milioni previsti 
 
   dall'azione organica 6.1, legge 1 marzo 1986, n. 64 del. 
 
   CIPE 3 agosto 1988 - +20.000.000. - +20.000.000. 
 
   Settore 4 
 
   Interventi plurisettoriali primo e secondo piano annuale di 
 
   attuazione. 
 
   21280206061034 - 11932 - Interventi relativi alla tutela 
 
   e salvaguardia dell'ambiente opere relative alla difesa 
 
   del suolo P.R.S. n. 1 legge 64/86 - +150.000.000 - 
 
   +150.000.000. 
 
   21280206061034 - 11945 - Interventi relativi allo sviluppo 
 
   e valorizzazione dell'agricoltura P.R.S. n. 2 attività di 
 
   integrazione del reddito a sostegno dell'agriturismo 
 
   finanziamento legge 183/87 legge regionale n. 2 del 25 gennaio 
 
   1994 - +1.124.100 - +1.124.100. 
 
   21280206061034 - 11953 - Interventi relativi allo sviluppo e 
 
   valorizzazione dell'agricoltura P.R.S. n. 2 potenziamento 
 
   infrastrutture rurali, realizzazione di strade e di acquedotti 
 
   in aree non irrigue, strade ed acquedotti in aree irrigue, 
 
   opere di bonifica integrale e montana e servizi di manutenzione 
 
   straordinaria di opere ed impianti dell'agricoltura. 
 
   Finanziamento legge 64/86 - +847.500 - +847.500. 
 
   21280206061034 - 11954 - Interventi relativi allo sviluppo 
 
   e valorizzazione dell'agricoltura. P.R.S. n. 2. 
 
   Realizzazione di strade ed acquedotti delle aree non irrigue 
 
   finanziamento CEE reg. 2052/88 - -1.854.170 - -1.854.120. 
 
   21280206061034 - 11955 - Interventi relativi allo 
 
   sviluppo e valorizzazione dell'agricoltura. P.R.S. n. 2. 
 
   Realizzazione di strade ed aquedotti nelle aree non irrigue. 
 
   Finanziamento art. 13 legge 64/86 - +1.556.490 - +1.556.490. 
 
   21280206061034 - 11973 - Interventi per l'attuazione dei 
 
   progetti regionali di sviluppo integrato territoriale. 
 
   P.R.S. n. 3. Valorizzazione della fascia costiera. 
 
   Finanziamento legge 64/86 - -200.000.000 - -200.000.000. 
 
   21280206071034 - 12010 - Fondo per l'attuazione di progetti 
 
   regionali di sviluppo relativi al potenziamento delle 
 
   strutture civili o sociali. (Legge 64 del 1 marzo 1986) - 
 
   +7.730.574 - +7.730.574. 
 
   21280206061034 - 12031 - Interventi volti alla razionalizzazione 
 
   e potenziamento del sistema dei trasporti. P.R.S. n. 7. 
 
   Finanziamento legge 64/86 - -46.856750 - -46.856.750. 
 
   21280206061034 - 12046 - Interventi volti allo sviluppo 
 
   e valorizzazione degli itinerari turistici culturali. 
 
   P.R.S. n. 8. Finanziamento legge 64/86 - -403.143.250 - 
 
   -403.143.250. 
 
   21280206011034 - 12090 - Oneri per l'attuazione del monitoraggio 
 
   dei progetti regionali di sviluppo. (Legge 64 del 1 marzo 1986). 
 
   P.O.P. Sottoprogramma n. 9 misura n. 1 - +514.912.500 - 
 
   +514.912.500. 
 
   Settore 5 
 
   Interventi plurisettoriali terzo piano annuale di attuazione. 
 
   12280206011035 - 12092 - Oneri relativi alla realizzazione 
 
   dei progetti inerenti il terzo piano di attuazione. Legge 64 
 
   lavori impianto Terme di Sepino - +400.000.000 - +400.000.000. 
 
   21280206011035 - 12207 - Oneri relativi al completamento 
 
   dei centri sociali. Terza annualità della legge 64/86. 
 
   (Delibera CIPE del 29 marzo 1990 D.C. n. 186 del 22 settembre 
 
   1992 - +500.000.000 - +500.000.000. 
 
   21280206011035 - 12208 - Oneri relativi all'occupazione 
 
   giovanile. Terza annualità della legge 64/86. (Delibera CIPE 
 
   del 29 marzo 1990 D.C. n. 186 del 22 settembre 1992 - 
 
   -20.000.000.000- -20.000.000.000. 
 
   21280206011035 - 12211 - Oneri relativi alle incentivazioni 
 
   a favore degli artigiani e delle aree attrezzate terza 
 
   annualità della legge 64/86. Delibera CIPE del 29 marzo 1990 
 
   D.C. n. 186 del 22 settembre 1992 - -10.000. 
 
   21280206011035 - 12228 - Fondo indiviso di contributi CEE 
 
   per il quadro comunitario di sostegno approvato dalla 
 
   commissione U.E. in data 5 luglio 1994. Regolamento CEE 
 
   n. 2081/93 del 20 luglio 1993. (Quota 1994/95). (Fondi 
 
   F.S.E. e FERS)- -147.331.700.000 - -147.331.700.000. 
 
   21280206011035 - 12229 - Fondo indiviso di contributi 
 
   nazionali per il piano di sviluppo regionale 1994/99 
 
   approvato dalla commissione U.E. in data 5 luglio 1994. 
 
   Regolamento CEE n. 2081/93 del 20 luglio 1994. (Quota 
 
   1994/95) - -62.701.900.000 - -62.701.900.000. 
 
   21280206011035 - 12230 - POP Molise interventi CEE fondi 
 
   FERS n. 940509003 per il finanziamento del sottoprogramma 
 
   n. 1 comunicazione (strade e autostrade ferrovie, ed altri 
 
   mezzi di trasporti) decisione CEE n.c. (94) 3776 del 
 
   20 dicembre 1994 - +16.096.000.000 - +16.096.000.000. 
 
   21280206011035 - 12231 - POP. Molise interventi statali sui 
 
   fondi FERS n. 94059003 per il finanziamento sottoprogramma 
 
   n. 1. Comunicazione (strade, autostrade ferrovie, altri 
 
   mezzi di trasporto) Del. CEE n. c. (94) 3766 del 20 dicembre 
 
   1994 - +9.448.000.000 - +9.448.000.000. 
 
   21280206011035 - 12232 - POP Molise. Interventi CEE con fondi 
 
   FERS n. 940509003 per il finanziamento del sottoprogramma 
 
   n. 2. Industria, artigianato e servizio alle imprese. Dec. CEE 
 
   n.c. (94) 3766 del 20 dicembre 1994 - +10.424.000.000 - 
 
   +10.424.000.000. 
 
   21280206011035 - 12233 - POP Molise interventi CEE con fondi 
 
   F.S.E. n. 940509003 per il finanziamento del sottoprogramma 
 
   n. 2. Industria, artigianato e servizio alle imprese. De. CEE 
 
   n.c. (94) 3766 del 20 dicembre 1994 - +2.800.000.000 - 
 
   +2.800.000.000. 
 
   21280206011035 - 12234 - POP Molise. Interventi statali 
 
   sui fondi F.E.R.S. n. 940509003 per il finanziamento del 
 
   sottoprogramma n. 2. Industria, artigianato e servizio 
 
   alle imprese. Decisione CEE n.c. (94) 3766 del 20 dicembre 
 
   1994 - +9.176.000.000 - +9.176.000.000. 
 
   21280206011035 - 12235 - POP. Molise. Interventi statali 
 
   sui fondi F.S.E. per il finanziamento del sottoprogramma 
 
   n. 2 industria artigianato e servizi alle imprese. 
 
   Dec. CEE n.c. (94) 3766 del 20 dicembre 1994 - 
 
   +932.000.000 - +932.000.000. 
 
   21280206011035 - 12236 - POP. Molise Interventi CEE con 
 
   fondi FERS n. 940509003 per il finanziamento del 
 
   programma n. 3 turismo, decisione CEE n.c. (94) 3766 
 
   del 20 dicembre 1994 - +2.564.000.000 - +2.564.000.000. 
 
   21280206011035 - 12237 - POP Molise. Interventi CEE con 
 
   fondi F.S.E. n. 940509003 per il finanziamento del 
 
   sottoprogramma n. 3. Turismo. Dec. CEE n.c. (94) 3766 
 
   del 20 dicembre 1994 - +1.600.000.000 - + 1.600.000.000. 
 
   21280206011035 - 12238 - POP. Molise. Interventi statali 
 
   sui fondi FERS n. 940509003 per il finanziamento del 
 
   programma n. 3. Turismo. Dec. CEE n.c. (94) 3766 del 
 
   20 dicembre 1994 - +2.708.000.000 - +2.708.000.000. 
 
   21280206011035 - 12239 - POP. Molise. Interventi statali 
 
   sui fondi F.S.E. n. 940509003 per il finanziamento del 
 
   sottoprogramma n. 3. Turismo. Dec. CEE n.c. (94) 3766 
 
   del 20 dicembre 1994 - +588.000.000 - +588.000.000. 
 
   21280206011035 - 12240 - POP. Molise. Interventi CEE sui 
 
   fondi F.S.E. n. 940509003 per il finanziamento del 
 
   programma n. 4. Diversificazione valorizzazione risorse 
 
   Agricole e sviluppo rurale. Dec. CEE n.c.(94) 3766 del 
 
   20 dicembre 1994- +2.666.000.000 - +2.666.000.000. 
 
   21280206011035 - 12241 - POP. Molise. Interventi statali 
 
   sui fondi F.S.E. n. 94509003 per il finanziamento del 
 
   programma n. 4. Diversificazione, valorizzazione agricole 
 
   e sviluppo rirale. Dec. CEE n.c. (94) 3766 del 20 dicembre 
 
   1994 - +888.000.000 - +888.000.000. 
 
   21280206011035 - 12242 - POP Molise. Interventi CEE sui fondi 
 
   FERS n. 94509003 per il finanziamento del programma n. 6. 
 
   Infrastrutture di supporto alle attività economiche. 
 
   Dec. CEE n.c. (94) 3766 del 20 dicembre 1994 - +15.674.000.000 - 
 
   +15.674.000.000. 
 
   21280206011035 - 12243 - POP. Molise Interventi CEE sui fondi 
 
   FSE n. 94509003 per il finanziamento del programma n. 6. 
 
   Infrastrutture di supporto alle attività economiche. 
 
   Dec. n.c. (94) 3766 del 20 dicembre 1994 - +3.064.000.000 - 
 
   +3.064.000.000. 
 
   21280206011035 - 12244 - POP. Molise. Interventi statali 
 
   sui fondi FERS n. 94509003 per il finanziamento del programma 
 
   n. 6. Infrastrutture di supporto alle attività economiche. Dec. 
 
   CEE n. c. (94) 3766 del 20 dicembre 1994 - +6.438.000.000 - 
 
   +6.438.000.000. 
 
   21280206011035 - 12245 - POP. Molise. Interventi statali sui fondi 
 
   FERS n. 94509003 per il finanziamento del programma n. 6. 
 
   Infrastrutture di supporto alle attività economiche. Dec. CEE 
 
   n.c. (94) 3766 del 20 dicembre 1994 - +444.000.000 - +444.000.000. 
 
   21280206011035 - 12246 - POP. Moliae. Interventi CEE sui fondi 
 
   F.S.E. n. 94509003 per il finanziamento del programma n. 7 
 
   Valorizzazione delle risorse umane. Dec. CEE n. c. (94) 3766 del 
 
   20 dicembre 1994 - +21.870.000.000 - +21.870.000.000. 
 
   21280206011035 - 12247 - POP. Molise. Interventi statali sui 
 
   fondi F.S.E. n. 94509003 per il finanziamento del programma n. 7. 
 
   Valorizzazione delle risorse umane. Dec. CEE n.c. (94) 3766 
 
   del 20 dicembre 1995 - +6.080.000.000 - +6.080.000.000. 
 
   21280206011035 - 12248 - PoOP. Molise. Interventi CEE sui fondi 
 
   F.E.R.S. n. 94509003 per il finanziamento del programma n. 8. 
 
   Assistenza tecnica pubblica e monitoraggio. Dec. CEE n.c. (94) 
 
   3766 del 20 dicembre 1995 - +318.000.000 - +318.000.000. 
 
   21280206011035 - 12249 - POP Molise. Interventi statali sui 
 
   fondi FERS n. 94509003 per il finanziamento del programma 
 
   n. 8. Assistenza tecnica pubblica e monitoraggio Dec. CEE n.c. 
 
   (94) 3766 del 20 dicembre 1994 - +136.000.000 - +136.000.000. 
 
   21280206011035 - 12300 - Oneri relativi agli interventi per 
 
   la promozione e lo sviluppo dell'imprenditorialità ed 
 
   interventi per il mantenimento dell'occupazione. Finalità di 
 
   cui al titolo I e II della legge regionale n. 24 dell'8 
 
   maggio 1995 - +10.000.000.000 - +10.000.000.000. 
 
   21280206011035 - 12301 - Oneri relativi agli interventi a 
 
   favore della formazione ed occupazione giovanile. Finalit&#x85; 
 
   del titolo III  della legge regionale n. 24 dell'8 maggio 1995. 
 
   - +5.000.000.000 - +5.000.000.000. 
 
   21280206011035 - 12302 - Oneri relativi agli interventi per 
 
   la promozione e sviluppo dell'imprenditorialità delegate alle 
 
   province. Finalità del titolo IV legge regionale n. 24 dell'8 
 
   maggio 1995 - +5.000.000.000 - +5.000.000.000. 
 
   21280206011035 - 12400 - Fondo indiviso per cofinanziamento 
 
   nazionale assegnato alla regione con delibera CIPE del 7 giugno 
 
   1993. Quota 93-94 legge 64/86 art. 13 - +24.996.278.000 - 
 
   +7.130.000.000. 
 
   Settore IV 
 
   Edilizia scolastica - Settore LL.PP. regionali degli Enti locali. 
 
   11232406042034 - 13700 - Contributi annui costanti ai comuni 
 
   per la costruzione di edifici scolastici (legge regionale 21 
 
   gennaio 1975, n. 10 let. c). Piano 1975 (leggi regionali 25 marzo 
 
   1977 n. 9 e 2 maggio 1977, n. 30) - 10 - +242.394.028 - 
 
   +242.394.028. 
 
   22262206052035 - 14200 - Attività di formazione ed addestramento 
 
   professionale legge regionale 17 gennaio 1983 n. 3 e legge 
 
   regionale n. 14 del 28 ottobre 1987 n. 27 e legge regionale 
 
   29 maggio 1990 e oneri personale docente e non docente a tempo 
 
   indeterminato impegnato nei corsi o in mobilità. Legge regionale 
 
   art. 7 legge regionale 27/90. Oneri pregressi. - +5.319.862.756. 
 
   - +5.319.862.756. 
 
   Rubrica IV 
 
   Attività culturali. settore 1 
 
   Musei e biblioteche di enti locali (settore musei bibliot. beni 
 
   cult.) 
 
   211522060062041 - 15600 - Oneri per lo svolgimento di attività 
 
   di competenza dei comuni per le funzioni di organizzazione e 
 
   gestione di servizi culturali (art.7 comma 4 legge regionale 
 
   11 dicembre 1980, n. 37). - -88.000.000. - -88.000.000. 
 
   Rubrica V 
 
   Sport e tempo libero. 
 
   Settore 1 
 
   Attività sportive (Settore turismo, sport, tempo libero). 
 
   2123208092051 - 16600 - Contirbuti regionali a favore dei Comuni 
 
   a titolo di concorso nella spesa per la gestione di impianti 
 
   sportivi e per l'acquisto di attrezzature anche di quelle 
 
   appartenenti a istituzioni, associazioni e sodalizi sportivi 
 
   regolarmente costituiti, pur se privi di personalità giuridica. 
 
   (Legge regionale n. 26 del 25 maggio 1990 art. 2 lett b e legge 
 
   regionale n. 14 del 26 luglio 1994) - +100.000.000 - +100.000.000. 
 
   21162208092051 - 16800 - Contributi a favore di associazioni e 
 
   società per lo svolgimento di attività sportive, dilettantistiche 
 
   e per l'impiego del tempo libero (legge regionale 9 novembre 1977, 
 
   n. 39 art. 2 let. d legge regionale 17 gennaio 1983, n. 4).- 
 
   -100.000.000 - -100.000.000. 
 
   21243309183071 - 18811 - Contributi in conto capitale per 
 
   investimenti nel trasporto pubblico locale previsti dall'art. 77 
 
 

?>
		</LeggeRegionale>
	</NIR>
